crick/tdigest.c
crick/tdigest_stubs.c
crick/stats.c
crick/space_saving_stubs.c
crick/common.h
crick/space_saving.cpython-310-i386-linux-gnu.so
crick/tdigest.cpython-310-i386-linux-gnu.so
crick/space_saving_stubs.c.in
crick/__init__.py
crick/stats.cpython-310-i386-linux-gnu.so
crick/tdigest.pyx
crick/stats_stubs.c
crick/stats.pyx
crick/space_saving.c
crick/_version.py
crick/numpy_version.c
crick/numpy_version_stubs.h
crick/numpy_version.cpython-310-i386-linux-gnu.so
crick/numpy_version.pyx
crick/space_saving.pyx
crick/tests/test_version.py
crick/tests/test_tdigest.py
crick/tests/test_space_saving.py
crick/tests/__init__.py
crick/tests/test_stats.py
crick/klib/khash.h
crick-0.0.8.dist-info/METADATA
crick-0.0.8.dist-info/RECORD
crick-0.0.8.dist-info/top_level.txt
crick-0.0.8.dist-info/WHEEL
crick-0.0.8.dist-info/LICENSE
