Metadata-Version: 2.1
Name: crick
Version: 0.0.8
Summary: High performance approximate and streaming algorithms
Maintainer-email: Jim Crist <crist042@umn.edu>
License: BSD-3-Clause
Project-URL: Source, https://github.com/dask/crick
Requires-Python: >=3.10
License-File: LICENSE
